{
  "entry_count": 10,
  "extra_source_urls": [],
  "fetched_at": "2026-05-26T01:11:05.249727Z",
  "notes": [
    "APKPure currently exposes a limited visible version catalog on this page; treat missing historical Android versions as source limitations, not absence of releases."
  ],
  "package_name": "com.teslamotors.tesla",
  "schema_version": 1,
  "source": "APKPure",
  "source_url": "https://apkpure.net/tesla/com.teslamotors.tesla/versions",
  "versions": [
    {
      "android_requirement": "Android 7.0+",
      "download_url": "https://apkpure.net/tesla/com.teslamotors.tesla/download",
      "file_size": "629.8 MB",
      "package_file_type": "XAPK",
      "package_name": "com.teslamotors.tesla",
      "source": "APKPure",
      "source_order": "0",
      "source_publish_date": "2026-05-14",
      "source_publish_date_raw": "May 14, 2026",
      "split_metadata": "XAPK",
      "stable_source_identifier": "/tesla/com.teslamotors.tesla/download",
      "supported_abis": "",
      "version_code": "4306",
      "version_name": "4.57.0-4306"
    },
    {
      "android_requirement": "Android 7.0+",
      "download_url": "https://apkpure.net/tesla/com.teslamotors.tesla/download/4.56.5-4281",
      "file_size": "380.6 MB",
      "package_file_type": "XAPK",
      "package_name": "com.teslamotors.tesla",
      "source": "APKPure",
      "source_order": "1",
      "source_publish_date": "2026-05-05",
      "source_publish_date_raw": "May 5, 2026",
      "split_metadata": "XAPK",
      "stable_source_identifier": "/tesla/com.teslamotors.tesla/download/4.56.5-4281",
      "supported_abis": "",
      "version_code": "4281",
      "version_name": "4.56.5-4281"
    },
    {
      "android_requirement": "Android 7.0+",
      "download_url": "https://apkpure.net/tesla/com.teslamotors.tesla/download/4.56.1-4255",
      "file_size": "610.3 MB",
      "package_file_type": "XAPK",
      "package_name": "com.teslamotors.tesla",
      "source": "APKPure",
      "source_order": "2",
      "source_publish_date": "2026-05-02",
      "source_publish_date_raw": "May 2, 2026",
      "split_metadata": "XAPK",
      "stable_source_identifier": "/tesla/com.teslamotors.tesla/download/4.56.1-4255",
      "supported_abis": "",
      "version_code": "4255",
      "version_name": "4.56.1-4255"
    },
    {
      "android_requirement": "Android 7.0+",
      "download_url": "https://apkpure.net/tesla/com.teslamotors.tesla/download/4.55.7-4234",
      "file_size": "616.6 MB",
      "package_file_type": "XAPK",
      "package_name": "com.teslamotors.tesla",
      "source": "APKPure",
      "source_order": "3",
      "source_publish_date": "2026-04-24",
      "source_publish_date_raw": "Apr 24, 2026",
      "split_metadata": "XAPK",
      "stable_source_identifier": "/tesla/com.teslamotors.tesla/download/4.55.7-4234",
      "supported_abis": "",
      "version_code": "4234",
      "version_name": "4.55.7-4234"
    },
    {
      "android_requirement": "Android 7.0+",
      "download_url": "https://apkpure.net/tesla/com.teslamotors.tesla/download/4.55.6-4229",
      "file_size": "616.6 MB",
      "package_file_type": "XAPK",
      "package_name": "com.teslamotors.tesla",
      "source": "APKPure",
      "source_order": "4",
      "source_publish_date": "2026-04-17",
      "source_publish_date_raw": "Apr 17, 2026",
      "split_metadata": "XAPK",
      "stable_source_identifier": "/tesla/com.teslamotors.tesla/download/4.55.6-4229",
      "supported_abis": "",
      "version_code": "4229",
      "version_name": "4.55.6-4229"
    },
    {
      "android_requirement": "Android 7.0+",
      "download_url": "https://apkpure.net/tesla/com.teslamotors.tesla/download/4.55.5-4193",
      "file_size": "584.4 MB",
      "package_file_type": "XAPK",
      "package_name": "com.teslamotors.tesla",
      "source": "APKPure",
      "source_order": "5",
      "source_publish_date": "2026-04-06",
      "source_publish_date_raw": "Apr 6, 2026",
      "split_metadata": "XAPK",
      "stable_source_identifier": "/tesla/com.teslamotors.tesla/download/4.55.5-4193",
      "supported_abis": "",
      "version_code": "4193",
      "version_name": "4.55.5-4193"
    },
    {
      "android_requirement": "Android 7.0+",
      "download_url": "https://apkpure.net/tesla/com.teslamotors.tesla/download/4.55.0-4166",
      "file_size": "620.4 MB",
      "package_file_type": "APK,XAPK",
      "package_name": "com.teslamotors.tesla",
      "source": "APKPure",
      "source_order": "6",
      "source_publish_date": "2026-03-24",
      "source_publish_date_raw": "Mar 24, 2026",
      "split_metadata": "APK,XAPK",
      "stable_source_identifier": "/tesla/com.teslamotors.tesla/download/4.55.0-4166",
      "supported_abis": "",
      "version_code": "4166",
      "version_name": "4.55.0-4166"
    },
    {
      "android_requirement": "Android 7.0+",
      "download_url": "https://apkpure.net/tesla/com.teslamotors.tesla/download/4.54.5-4133",
      "file_size": "536.1 MB",
      "package_file_type": "XAPK",
      "package_name": "com.teslamotors.tesla",
      "source": "APKPure",
      "source_order": "7",
      "source_publish_date": "2026-03-11",
      "source_publish_date_raw": "Mar 11, 2026",
      "split_metadata": "XAPK",
      "stable_source_identifier": "/tesla/com.teslamotors.tesla/download/4.54.5-4133",
      "supported_abis": "",
      "version_code": "4133",
      "version_name": "4.54.5-4133"
    },
    {
      "android_requirement": "Android 7.0+",
      "download_url": "https://apkpure.net/tesla/com.teslamotors.tesla/download/4.54.0-4094",
      "file_size": "532.4 MB",
      "package_file_type": "XAPK",
      "package_name": "com.teslamotors.tesla",
      "source": "APKPure",
      "source_order": "8",
      "source_publish_date": "2026-03-06",
      "source_publish_date_raw": "Mar 6, 2026",
      "split_metadata": "XAPK",
      "stable_source_identifier": "/tesla/com.teslamotors.tesla/download/4.54.0-4094",
      "supported_abis": "",
      "version_code": "4094",
      "version_name": "4.54.0-4094"
    },
    {
      "android_requirement": "Android 7.0+",
      "download_url": "https://apkpure.net/tesla/com.teslamotors.tesla/download/4.54.3-4107",
      "file_size": "573.1 MB",
      "package_file_type": "APK",
      "package_name": "com.teslamotors.tesla",
      "source": "APKPure",
      "source_order": "9",
      "source_publish_date": "2026-03-02",
      "source_publish_date_raw": "Mar 2, 2026",
      "split_metadata": "APK",
      "stable_source_identifier": "/tesla/com.teslamotors.tesla/download/4.54.3-4107",
      "supported_abis": "",
      "version_code": "4107",
      "version_name": "4.54.3-4107"
    }
  ]
}
